MANIFEST.in
README.md
requirements.txt
setup.py
ucloud_cli/__init__.py
ucloud_cli/cli.py
ucloud_cli/doc.json
ucloud_cli/enums.json
ucloud_cli/gen_doc.py
ucloud_cli.egg-info/PKG-INFO
ucloud_cli.egg-info/SOURCES.txt
ucloud_cli.egg-info/dependency_links.txt
ucloud_cli.egg-info/entry_points.txt
ucloud_cli.egg-info/requires.txt
ucloud_cli.egg-info/top_level.txt