Metadata-Version: 1.1
Name: ucloud-cli
Version: 0.6
Summary: A simple command-line tool for interacting with UCloud API.
Home-page: https://github.com/likang/ucloud-cli
Author: Kang Li
Author-email: i@likang.me
License: MIT
Download-URL: http://pypi.python.org/pypi/ucloud-cli
Keywords: ucloud,console,commandline,command
Platform: any
Classifier: Intended Audience :: Developers
Classifier: License :: OSI Approved :: MIT License
Classifier: Operating System :: OS Independent
Classifier: Programming Language :: Python
Classifier: Programming Language :: Python :: 2
Classifier: Programming Language :: Python :: 2.7
